{
  "name": "Localhost",
  "chain": "ETH",
  "rpc": [
    "http://localhost:8545"
  ],
  "faucets": [],
  "nativeCurrency": {
    "name": "Ether",
    "symbol": "ETH",
    "decimals": 18
  },
  "shortName": "local",
  "chainId": 1337,
  "networkId": 1337,
  "testnet": true,
  "icon": {
    "url": "ipfs://QmcxZHpyJa8T4i63xqjPYrZ6tKrt55tZJpbXcjSDKuKaf9/arbitrum/512.png",
    "height": 512,
    "width": 512,
    "format": "png",
    "sizes": [
      512,
      256,
      128,
      64,
      32,
      16
    ]
  },
  "slug": "localhost"
}